{
    "locations": [
        {
            "type": "Landmark",
            "nation": "Earth Kingdom",
            "properties": {
                "CITY_ID": 101,
                "NAME": "The Swamp",
                "DESCRIPTION": "Massive swamp filled with mysterious 'spirit energy'"
            },
            "geometry": {
                "type": "Point",
                "coordinates": [52, 278]
            }
        },
        {
            "type": "Landmark",
            "nation": "Earth Kingdom",
            "properties": {
                "CITY_ID": 102,
                "NAME": "HeiBai's Forest",
                "DESCRIPTION": "Home to the spirit, HaiBai. The forest was burned down by the Fire Nation during the 100 Year War"
            },
            "geometry": {
                "type": "Point",
                "coordinates": [127, 225]
            }
        },
        {
            "type": "Landmark",
            "nation": "Earth Kingdom",
            "properties": {
                "CITY_ID": 103,
                "NAME": "Serpent's Pass",
                "DESCRIPTION": "Dangerous land bridge whose water is home to a giant sea serpent"
            },
            "geometry": {
                "type": "Point",
                "coordinates": [151, 316]
            }
        },
        {
            "type": "Landmark",
            "nation": "Earth Kingdom",
            "properties": {
                "CITY_ID": 104,
                "NAME": "The Library",
                "DESCRIPTION": "A giant library under the sands of the desert. Run by the spirit Wan Shi Tong"
            },
            "geometry": {
                "type": "Point",
                "coordinates": [85, 350]
            }
        },
        {
            "type": "Landmark",
            "nation": "Earth Kingdom",
            "properties": {
                "CITY_ID": 105,
                "NAME": "Lake Laogai",
                "DESCRIPTION": "Lake in Ba Sing Se with prisons and secret rooms for Earth Kingdom prisoners and brainwashings"
            },
            "geometry": {
                "type": "Point",
                "coordinates": [177, 392]
            }
        },

        {
            "type": "Landmark",
            "nation": "Earth Kingdom",
            "properties": {
                "CITY_ID": 106,
                "NAME": "Jet's Forest",
                "DESCRIPTION": "Home to Jet and his gang after they lost their homes to the Fire Nation"
            },
            "geometry": {
                "type": "Point",
                "coordinates": [146, 242]
            }
        },
        {
            "type": "Landmark",
            "nation": "Earth Kingdom",
            "properties": {
                "CITY_ID": 107,
                "NAME": "The Great Divide",
                "DESCRIPTION": "Giant Canyon. The only way to cross is with a canyone guide that knows earthbending. DO NOT BRING FOOD INTO THE CANYON"
            },
            "geometry": {
                "type": "Point",
                "coordinates": [135, 274]
            }
        },
        {
            "type": "Landmark",
            "nation": "Earth Kingdom",
            "properties": {
                "CITY_ID": 108,
                "NAME": "Lovers' Cave",
                "DESCRIPTION": "Cave of Two Lovers infamous for travellers getting lost. If you can find your way through, you will arrive at Omashu"
            },
            "geometry": {
                "type": "Point",
                "coordinates": [80, 258]
            }
        },
        {
            "type": "Landmark",
            "nation": "Earth Kingdom",
            "properties": {
                "CITY_ID": 109,
                "NAME": "Chameleon Bay",
                "DESCRIPTION": "Where Avatar Aang and his friends meet up with Hakoda and the rest of the invasion group"
            },
            "geometry": {
                "type": "Point",
                "coordinates": [110, 413]
            }
        },
        {
            "type": "Landmark",
            "nation": "Earth Kingdom",
            "properties": {
                "CITY_ID": 110,
                "NAME": "Sheltered Cove",
                "DESCRIPTION": ""
            },
            "geometry": {
                "type": "Point",
                "coordinates": [120, 168.5]
            }
        },
        {
            "type": "Landmark",
            "nation": "Earth Kingdom",
            "properties": {
                "CITY_ID": 111,
                "NAME": "Black Cliffs",
                "DESCRIPTION": ""
            },
            "geometry": {
                "type": "Point",
                "coordinates": [96, 80]
            }
        },
        {
            "type": "Landmark",
            "nation": "Earth Kingdom",
            "properties": {
                "CITY_ID": 112,
                "NAME": "Gates of Azulon",
                "DESCRIPTION": ""
            },
            "geometry": {
                "type": "Point",
                "coordinates": [96, 67]
            }
        },
        {
            "type": "Landmark",
            "nation": "Earth Kingdom",
            "properties": {
                "CITY_ID": 113,
                "NAME": "Whale Tale Island",
                "DESCRIPTION": ""
            },
            "geometry": {
                "type": "Point",
                "coordinates": [17, 225]
            }
        }
    ]
}
